diffbot_nlapi/__init__.py
diffbot_nlapi/api_client.py
diffbot_nlapi/configuration.py
diffbot_nlapi/rest.py
diffbot_nlapi/api/__init__.py
diffbot_nlapi/api/natural_language_api.py
diffbot_nlapi/models/__init__.py
diffbot_nlapi/models/document.py
diffbot_nlapi/models/document_array.py
diffbot_nlapi/models/entity.py
diffbot_nlapi/models/entity_candidate.py
diffbot_nlapi/models/entity_type.py
diffbot_nlapi/models/entity_with_mentions.py
diffbot_nlapi/models/error_response.py
diffbot_nlapi/models/evidence.py
diffbot_nlapi/models/mention.py
diffbot_nlapi/models/mention_with_entities.py
diffbot_nlapi/models/mention_with_entity_candidates.py
diffbot_nlapi/models/model_property.py
diffbot_nlapi/models/natural_language_response.py
diffbot_nlapi/models/natural_language_response_array.py
diffbot_nlapi/models/qualifier.py
diffbot_nlapi/models/span.py
diffbot_nlapi/models/statement.py
diffbot_nlapi/models/statement_entity.py
diffbot_nlapi-0.0.3.dist-info/METADATA
diffbot_nlapi-0.0.3.dist-info/WHEEL
diffbot_nlapi-0.0.3.dist-info/top_level.txt
diffbot_nlapi-0.0.3.dist-info/RECORD
