Metadata-Version: 2.1
Name: diffbot-nlapi
Version: 0.0.3
Summary: Natural Language Understanding
Home-page: https://www.diffbot.com/
Author: UNKNOWN
Author-email: jay@diffbot.com
License: UNKNOWN
Keywords: Diffbot,Natural Language Understanding
Platform: UNKNOWN
Requires-Dist: certifi (>=2017.4.17)
Requires-Dist: python-dateutil (>=2.1)
Requires-Dist: six (>=1.10)
Requires-Dist: urllib3 (>=1.23)
